nose2/__init__.py
nose2/__main__.py
nose2/_toml.py
nose2/collector.py
nose2/config.py
nose2/events.py
nose2/exceptions.py
nose2/loader.py
nose2/main.py
nose2/result.py
nose2/runner.py
nose2/session.py
nose2/sphinxext.py
nose2/suite.py
nose2/util.py
nose2/plugins/__init__.py
nose2/plugins/_constants.py
nose2/plugins/attrib.py
nose2/plugins/buffer.py
nose2/plugins/collect.py
nose2/plugins/coverage.py
nose2/plugins/debugger.py
nose2/plugins/doctests.py
nose2/plugins/dundertest.py
nose2/plugins/failfast.py
nose2/plugins/junitxml.py
nose2/plugins/layers.py
nose2/plugins/logcapture.py
nose2/plugins/mp.py
nose2/plugins/outcomes.py
nose2/plugins/prettyassert.py
nose2/plugins/printhooks.py
nose2/plugins/prof.py
nose2/plugins/result.py
nose2/plugins/testid.py
nose2/plugins/loader/__init__.py
nose2/plugins/loader/discovery.py
nose2/plugins/loader/eggdiscovery.py
nose2/plugins/loader/functions.py
nose2/plugins/loader/generators.py
nose2/plugins/loader/loadtests.py
nose2/plugins/loader/parameters.py
nose2/plugins/loader/testcases.py
nose2/plugins/loader/testclasses.py
nose2/tests/__init__.py
nose2/tests/_common.py
nose2/tests/functional/__init__.py
nose2/tests/functional/test_attrib_plugin.py
nose2/tests/functional/test_collect_plugin.py
nose2/tests/functional/test_coverage.py
nose2/tests/functional/test_decorators.py
nose2/tests/functional/test_discovery_loader.py
nose2/tests/functional/test_doctests_plugin.py
nose2/tests/functional/test_dundertest_plugin.py
nose2/tests/functional/test_eggdiscovery_loader.py
nose2/tests/functional/test_junitxml_plugin.py
nose2/tests/functional/test_layers_hooks.py
nose2/tests/functional/test_layers_plugin.py
nose2/tests/functional/test_loading.py
nose2/tests/functional/test_loadtests_plugin.py
nose2/tests/functional/test_logcapture_plugin.py
nose2/tests/functional/test_main.py
nose2/tests/functional/test_mp_plugin.py
nose2/tests/functional/test_prettyassert.py
nose2/tests/functional/test_printhooks_plugin.py
nose2/tests/functional/support/scenario/tests_in_unzipped_eggs/pkgunegg-0.0.0-py2.7.egg/EGG-INFO/SOURCES.txt
nose2/tests/functional/support/scenario/tests_in_unzipped_eggs/pkgunegg-0.0.0-py2.7.egg/EGG-INFO/dependency_links.txt
nose2/tests/functional/support/scenario/tests_in_unzipped_eggs/pkgunegg-0.0.0-py2.7.egg/EGG-INFO/top_level.txt
nose2-0.15.1.dist-info/AUTHORS
nose2-0.15.1.dist-info/LICENSE
nose2-0.15.1.dist-info/METADATA
nose2-0.15.1.dist-info/WHEEL
nose2-0.15.1.dist-info/entry_points.txt
nose2-0.15.1.dist-info/top_level.txt
nose2-0.15.1.dist-info/RECORD
