Metadata-Version: 2.1
Name: nose2
Version: 0.15.1
Summary: unittest with plugins
Author-email: Stephen Rosen <dev@nose2.io>
License: BSD-2-Clause
Project-URL: changelog, https://docs.nose2.io/en/latest/changelog.html
Project-URL: documentation, https://docs.nose2.io/
Project-URL: repository, https://github.com/nose-devs/nose2
Keywords: testing,tests,unittest
Classifier: Development Status :: 4 - Beta
Classifier: Environment :: Console
Classifier: Intended Audience :: Developers
Classifier: License :: OSI Approved :: BSD License
Classifier: Operating System :: OS Independent
Classifier: Programming Language :: Python
Classifier: Programming Language :: Python :: 3 :: Only
Classifier: Programming Language :: Python :: 3.8
Classifier: Programming Language :: Python :: 3.9
Classifier: Programming Language :: Python :: 3.10
Classifier: Programming Language :: Python :: 3.11
Classifier: Programming Language :: Python :: 3.12
Classifier: Programming Language :: Python :: Implementation :: CPython
Classifier: Programming Language :: Python :: Implementation :: PyPy
Classifier: Topic :: Software Development :: Libraries
Classifier: Topic :: Software Development :: Libraries :: Python Modules
Classifier: Topic :: Software Development :: Testing
Requires-Python: >=3.8
License-File: LICENSE
License-File: AUTHORS
Provides-Extra: coverage-plugin
Requires-Dist: coverage; extra == "coverage-plugin"
Provides-Extra: dev
Requires-Dist: sphinx; extra == "dev"
Requires-Dist: sphinx-issues; extra == "dev"
Requires-Dist: sphinx-rtd-theme; extra == "dev"
